<T3DataStructure>
	<meta>
		<langDisable>1</langDisable>
	</meta>
	<sheets>
		<sDEF>
			<ROOT>
				<TCEforms>
					<sheetTitle>LLL:EXT:tnt_blumenshop/Resources/Private/Language/locallang_db.xml:ff.sheetTitle1</sheetTitle>
				</TCEforms>
				<type>array</type>
				<el>
					<settings.flexform.from_email>
						<TCEforms>
							<label>LLL:EXT:tnt_blumenshop/Resources/Private/Language/locallang_db.xml:ff.from_email</label>
							<config>
								<type>input</type>
								<size>20</size>
							</config>
						</TCEforms>
					</settings.flexform.from_email>
					<settings.flexform.admin_email>
						<TCEforms>
							<label>LLL:EXT:tnt_blumenshop/Resources/Private/Language/locallang_db.xml:ff.admin_email</label>
							<config>
								<type>input</type>
								<size>20</size>
							</config>
						</TCEforms>
					</settings.flexform.admin_email>
					<settings.flexform.cat>
						<TCEforms>
							<label>LLL:EXT:tnt_blumenshop/Resources/Private/Language/locallang_db.xml:ff.choose_category</label>
							<config>
								 <type>select</type>
								 <foreign_table>tx_tntblumenshop_cat</foreign_table>
								 <foreign_table_where>AND tx_tntblumenshop_cat.hidden = 0 AND tx_tntblumenshop_cat.deleted = 0 ORDER BY tx_tntblumenshop_cat.uid</foreign_table_where>
								 <size>5</size>
								 <minitems>0</minitems>
      							 <maxitems>999</maxitems>
							</config>
						</TCEforms>
					</settings.flexform.cat>
					<settings.flexform.price_extra1>
						<TCEforms>
							<label>LLL:EXT:tnt_blumenshop/Resources/Private/Language/locallang_db.xml:ff.price_extra1</label>
							<config>
								<type>input</type>
								<size>10</size>
							</config>
						</TCEforms>
					</settings.flexform.price_extra1>
					<settings.flexform.price_extra2>
						<TCEforms>
							<label>LLL:EXT:tnt_blumenshop/Resources/Private/Language/locallang_db.xml:ff.price_extra2</label>
							<config>
								<type>input</type>
								<size>10</size>
							</config>
						</TCEforms>
					</settings.flexform.price_extra2>
					<settings.flexform.title>
						<TCEforms>
							<label>LLL:EXT:tnt_blumenshop/Resources/Private/Language/locallang_db.xml:ff.title</label>
							<config>
								<type>input</type>
								<size>20</size>
							</config>
						</TCEforms>
					</settings.flexform.title>
					<settings.flexform.intro_text>
						<TCEforms>
							<label>LLL:EXT:tnt_blumenshop/Resources/Private/Language/locallang_db.xml:ff.intro_text</label>
							<config>
								<type>text</type>
  								<cols>40</cols>
 								<rows>5</rows>
							</config>
						</TCEforms>
					</settings.flexform.intro_text>
					<settings.flexform.payment_message>
						<TCEforms>
							<label>LLL:EXT:tnt_blumenshop/Resources/Private/Language/locallang_db.xml:ff.payment_message</label>
							<config>
								 <type>check</type>
							</config>
						</TCEforms>
					</settings.flexform.payment_message>
				</el>
			</ROOT>
	    </sDEF>
	    <display>
			<ROOT>
				<TCEforms>
					<sheetTitle>LLL:EXT:tnt_blumenshop/Resources/Private/Language/locallang_db.xml:ff.sheetTitle2</sheetTitle>
				</TCEforms>	
				<type>array</type>
				<el>
					<settings.flexform.merchantid>
						<TCEforms>
							<label>LLL:EXT:tnt_blumenshop/Resources/Private/Language/locallang_db.xml:ff.merchantid</label>
							<config>
								<type>input</type>
								<size>20</size>
							</config>
						</TCEforms>
					</settings.flexform.merchantid>
					<settings.flexform.paymenturl>
						<TCEforms>
							<label>LLL:EXT:tnt_blumenshop/Resources/Private/Language/locallang_db.xml:ff.paymenturl</label>
							<config>
								<type>input</type>
								<size>30</size>
							</config>
						</TCEforms>
					</settings.flexform.paymenturl>
					<settings.flexform.successurl>
						<TCEforms>
							<label>LLL:EXT:tnt_blumenshop/Resources/Private/Language/locallang_db.xml:ff.successurl</label>
							<config>
								<type>input</type>
								<size>30</size>
							</config>
						</TCEforms>
					</settings.flexform.successurl>
					<settings.flexform.errorurl>
						<TCEforms>
							<label>LLL:EXT:tnt_blumenshop/Resources/Private/Language/locallang_db.xml:ff.errorurl</label>
							<config>
								<type>input</type>
								<size>30</size>
							</config>
						</TCEforms>
					</settings.flexform.errorurl>
					<settings.flexform.cancelurl>
						<TCEforms>
							<label>LLL:EXT:tnt_blumenshop/Resources/Private/Language/locallang_db.xml:ff.cancelurl</label>
							<config>
								<type>input</type>
								<size>30</size>
							</config>
						</TCEforms>
					</settings.flexform.cancelurl>
				</el>
			</ROOT>
	    </display>
	</sheets>
</T3DataStructure>

